peaq_robot/__init__.py
peaq_robot/access.py
peaq_robot/core.py
peaq_robot/did_document_format_pb2.py
peaq_robot/identity.py
peaq_robot/py.typed
peaq_robot/storage.py
peaq_robot/types.py
peaq_robot/wallet.py
peaq_robot/robotics/__init__.py
peaq_robot/robotics/access_control.py
peaq_robot/robotics/base_robot.py
peaq_robot/robotics/data_vault.py
peaq_robot/robotics/events.py
peaq_robot/robotics/identity_service.py
peaq_robot/robotics/triggers.py
peaq_robot/robotics/unitree_g1.py
peaq_robot/utils/config.py
peaq_robot/utils/encoding.py
peaq_robot/utils/keystore.py
peaq_robot/utils/logger.py
peaq_robot/utils/validation.py
peaq_robotics_sdk-0.0.2.dist-info/METADATA
peaq_robotics_sdk-0.0.2.dist-info/WHEEL
peaq_robotics_sdk-0.0.2.dist-info/top_level.txt
peaq_robotics_sdk-0.0.2.dist-info/RECORD
