Metadata-Version: 2.4
Name: peaq-robotics-sdk
Version: 0.0.2
Summary: peaq Robot SDK for robotics on the peaq network (Substrate)
Home-page: https://github.com/peaqNetwork/peaq-robotics-sdk
Author: peaq
Author-email: info@peaq.xyz
License: Apache-2.0
Classifier: Development Status :: 4 - Beta
Classifier: Programming Language :: Python :: 3
Classifier: Programming Language :: Python :: 3.8
Classifier: Programming Language :: Python :: 3.9
Classifier: Programming Language :: Python :: 3.10
Classifier: Programming Language :: Python :: 3.11
Classifier: Programming Language :: Python :: 3.12
Classifier: Operating System :: OS Independent
Requires-Python: <3.13,>=3.8
Requires-Dist: substrate-interface<2.0.0,>=1.7.11
Requires-Dist: cryptography>=41.0.0
Requires-Dist: protobuf>=5.0.0
Requires-Dist: pydantic>=2.6.0
